{"container_type": "Author", "filled": ["basics", "publications", "indices", "counts"], "scholar_id": "SCHOLAR_ID&user=S7yHOaYAAAAJ", "source": "AUTHOR_PROFILE_PAGE", "name": "Zijie Wang (王子杰)", "affiliation": "Unknown affiliation", "interests": [], "citedby": 18, "publications": {"S7yHOaYAAAAJ:9yKSN-GCB0IC": {"container_type": "Publication", "source": "AUTHOR_PUBLICATION_ENTRY", "bib": {"title": "Automatic recognition algorithm of the lightning whistler waves by using speech processing technology", "pub_year": "2022"}, "filled": false, "author_pub_id": "S7yHOaYAAAAJ:9yKSN-GCB0IC", "num_citations": 16, "citedby_url": "https://scholar.google.com/scholar?oi=bibs&hl=en&cites=4017677271261242803", "cites_id": ["4017677271261242803"]}, "S7yHOaYAAAAJ:d1gkVwhDpl0C": {"container_type": "Publication", "source": "AUTHOR_PUBLICATION_ENTRY", "bib": {"title": "Lightning-generated Whistlers recognition for accurate disaster monitoring in China and its surrounding areas based on a homologous dual-feature information enhancement framework", "pub_year": "2024"}, "filled": false, "author_pub_id": "S7yHOaYAAAAJ:d1gkVwhDpl0C", "num_citations": 2, "citedby_url": "https://scholar.google.com/scholar?oi=bibs&hl=en&cites=5693127383510362180", "cites_id": ["5693127383510362180"]}, "S7yHOaYAAAAJ:UeHWp8X0CEIC": {"container_type": "Publication", "source": "AUTHOR_PUBLICATION_ENTRY", "bib": {"title": "Accurate semantic segmentation of very high-resolution remote sensing images considering feature state sequences: From benchmark datasets to urban applications", "pub_year": "2025"}, "filled": false, "author_pub_id": "S7yHOaYAAAAJ:UeHWp8X0CEIC", "num_citations": 0}, "S7yHOaYAAAAJ:qjMakFHDy7sC": {"container_type": "Publication", "source": "AUTHOR_PUBLICATION_ENTRY", "bib": {"title": "Automatic Recognition of the Lighting Whistler waves from the Wave Data of SCM Boarded on ZH-1 satellite", "pub_year": "2021"}, "filled": false, "author_pub_id": "S7yHOaYAAAAJ:qjMakFHDy7sC", "num_citations": 0}}, "citedby5y": 18, "hindex": 2, "hindex5y": 2, "i10index": 1, "i10index5y": 1, "cites_per_year": {"2022": 1, "2023": 5, "2024": 11, "2025": 1}, "updated": "2025-02-14 08:09:57.878268"}